{"data":{"allMarkdownRemark":{"totalCount":11,"edges":[{"node":{"fields":{"slug":null},"frontmatter":{"title":""}}},{"node":{"fields":{"slug":null},"frontmatter":{"title":""}}},{"node":{"fields":{"slug":null},"frontmatter":{"title":""}}},{"node":{"fields":{"slug":null},"frontmatter":{"title":""}}},{"node":{"fields":{"slug":null},"frontmatter":{"title":""}}},{"node":{"fields":{"slug":null},"frontmatter":{"title":""}}},{"node":{"fields":{"slug":null},"frontmatter":{"title":""}}},{"node":{"fields":{"slug":null},"frontmatter":{"title":""}}},{"node":{"fields":{"slug":"/blog/2018-06-18-why-narative-loves-gatsby/"},"frontmatter":{"title":"Why Narative loves Gatsby"}}},{"node":{"fields":{"slug":"/blog/2017-05-31-introduction-to-gatsby/"},"frontmatter":{"title":"Introduction to Gatsby"}}},{"node":{"fields":{"slug":"/blog/2017-07-19-creating-a-blog-with-gatsby/"},"frontmatter":{"title":"Creating a Blog with Gatsby"}}}]}},"pageContext":{"tag":"blog"}}