{"data":{"markdownRemark":{"html":"<h1 id=\"gatsby-plugin-emotion\"><a href=\"#gatsby-plugin-emotion\" aria-hidden=\"true\" class=\"anchor\"><svg aria-hidden=\"true\" height=\"16\" version=\"1.1\" viewBox=\"0 0 16 16\" width=\"16\"><path fill-rule=\"evenodd\" d=\"M4 9h1v1H4c-1.5 0-3-1.69-3-3.5S2.55 3 4 3h4c1.45 0 3 1.69 3 3.5 0 1.41-.91 2.72-2 3.25V8.59c.58-.45 1-1.27 1-2.09C10 5.22 8.98 4 8 4H4c-.98 0-2 1.22-2 2.5S3 9 4 9zm9-3h-1v1h1c1 0 2 1.22 2 2.5S13.98 12 13 12H9c-.98 0-2-1.22-2-2.5 0-.83.42-1.64 1-2.09V6.25c-1.09.53-2 1.84-2 3.25C6 11.31 7.55 13 9 13h4c1.45 0 3-1.69 3-3.5S14.5 6 13 6z\"></path></svg></a>gatsby-plugin-emotion</h1>\n<p>Provide support for using the css-in-js library\n<a href=\"https://github.com/emotion-js/emotion\">Emotion</a> including server side\nrendering.</p>\n<h2 id=\"install\"><a href=\"#install\" aria-hidden=\"true\" class=\"anchor\"><svg aria-hidden=\"true\" height=\"16\" version=\"1.1\" viewBox=\"0 0 16 16\" width=\"16\"><path fill-rule=\"evenodd\" d=\"M4 9h1v1H4c-1.5 0-3-1.69-3-3.5S2.55 3 4 3h4c1.45 0 3 1.69 3 3.5 0 1.41-.91 2.72-2 3.25V8.59c.58-.45 1-1.27 1-2.09C10 5.22 8.98 4 8 4H4c-.98 0-2 1.22-2 2.5S3 9 4 9zm9-3h-1v1h1c1 0 2 1.22 2 2.5S13.98 12 13 12H9c-.98 0-2-1.22-2-2.5 0-.83.42-1.64 1-2.09V6.25c-1.09.53-2 1.84-2 3.25C6 11.31 7.55 13 9 13h4c1.45 0 3-1.69 3-3.5S14.5 6 13 6z\"></path></svg></a>Install</h2>\n<div class=\"gatsby-highlight\" data-language=\"text\">\n      <pre class=\"language-text\"><code class=\"language-text\">npm install --save gatsby-plugin-emotion emotion emotion-server react-emotion</code></pre>\n      </div>\n<h2 id=\"how-to-use\"><a href=\"#how-to-use\" aria-hidden=\"true\" class=\"anchor\"><svg aria-hidden=\"true\" height=\"16\" version=\"1.1\" viewBox=\"0 0 16 16\" width=\"16\"><path fill-rule=\"evenodd\" d=\"M4 9h1v1H4c-1.5 0-3-1.69-3-3.5S2.55 3 4 3h4c1.45 0 3 1.69 3 3.5 0 1.41-.91 2.72-2 3.25V8.59c.58-.45 1-1.27 1-2.09C10 5.22 8.98 4 8 4H4c-.98 0-2 1.22-2 2.5S3 9 4 9zm9-3h-1v1h1c1 0 2 1.22 2 2.5S13.98 12 13 12H9c-.98 0-2-1.22-2-2.5 0-.83.42-1.64 1-2.09V6.25c-1.09.53-2 1.84-2 3.25C6 11.31 7.55 13 9 13h4c1.45 0 3-1.69 3-3.5S14.5 6 13 6z\"></path></svg></a>How to use</h2>\n<p>Add the plugin to your <code class=\"language-text\">gatsby-config.js</code>.</p>\n<div class=\"gatsby-highlight\" data-language=\"js\">\n      <pre class=\"language-js\"><code class=\"language-js\">module<span class=\"token punctuation\">.</span>exports <span class=\"token operator\">=</span> <span class=\"token punctuation\">{</span>\n    plugins<span class=\"token punctuation\">:</span> <span class=\"token punctuation\">[</span>\n        <span class=\"token punctuation\">{</span>\n            resolve<span class=\"token punctuation\">:</span> <span class=\"token template-string\"><span class=\"token string\">`gatsby-plugin-emotion`</span></span><span class=\"token punctuation\">,</span>\n            options<span class=\"token punctuation\">:</span> <span class=\"token punctuation\">{</span>\n                <span class=\"token comment\">// Accepts all options defined by `babel-plugin-emotion` plugin.</span>\n            <span class=\"token punctuation\">}</span>\n        <span class=\"token punctuation\">}</span>\n    <span class=\"token punctuation\">]</span>\n<span class=\"token punctuation\">]</span><span class=\"token punctuation\">;</span></code></pre>\n      </div>","excerpt":"gatsby-plugin-emotion Provide support for using the css-in-js library\n Emotion  including server side\nrendering. Install How to use Add the…","timeToRead":1,"fields":{"title":"gatsby-plugin-emotion"},"parent":{"__typename":"File","relativePath":"gatsby-plugin-emotion/README.md"}},"npmPackage":{"name":"gatsby-plugin-emotion","keywords":["emotion","gatsby","gatsby-plugin"],"lastPublisher":{"name":"kylemathews","avatar":"https://gravatar.com/avatar/e567aa8adbd2d49cd9990ea1ed19d4eb"}}},"pageContext":{"slug":"/packages/gatsby-plugin-emotion/","id":"85582609-6127-533f-8ec7-860f8506843e"}}